testpackage/__init__.py
yashsalvi_testpackage-0.3.dist-info/LICENCE.txt
yashsalvi_testpackage-0.3.dist-info/METADATA
yashsalvi_testpackage-0.3.dist-info/WHEEL
yashsalvi_testpackage-0.3.dist-info/top_level.txt
yashsalvi_testpackage-0.3.dist-info/RECORD
