Metadata-Version: 2.1
Name: yashsalvi-testpackage
Version: 0.3
Summary: Dummy File
Author: Yash Salvi
Author-email: <yash.salvi@proteustech.in>
Keywords: python,first package
Classifier: Development Status :: 3 - Alpha
Classifier: Intended Audience :: Education
Classifier: Programming Language :: Python :: 2
Classifier: Programming Language :: Python :: 3
Classifier: Operating System :: MacOS :: MacOS X
Classifier: Operating System :: Microsoft :: Windows
License-File: LICENCE.txt
